sql_mongo_converter/__init__.py
sql_mongo_converter/benchmark.py
sql_mongo_converter/cli.py
sql_mongo_converter/converter.py
sql_mongo_converter/exceptions.py
sql_mongo_converter/logger.py
sql_mongo_converter/mongo_to_sql.py
sql_mongo_converter/sql_to_mongo.py
sql_mongo_converter/validator.py
sql_mongo_converter-2.1.0.dist-info/licenses/LICENSE
sql_mongo_converter-2.1.0.dist-info/METADATA
sql_mongo_converter-2.1.0.dist-info/WHEEL
sql_mongo_converter-2.1.0.dist-info/entry_points.txt
sql_mongo_converter-2.1.0.dist-info/top_level.txt
sql_mongo_converter-2.1.0.dist-info/RECORD
